[
    {
        "name": "Calyrex-Shadow",
        "item": "Life Orb",
        "gender": "Genderless",
        "ability": "As One (Spectrier)",
        "level": 50,
        "tera_type": "Dark",
        "nature": "Timid",
        "evs": {
            "ev_hp": 20,
            "ev_attack": 92,
            "ev_defense": 4,
            "ev_special_attack": 228,
            "ev_special_defense": 4,
            "ev_speed": 252
        },
        "ivs": {
            "iv_hp": 31,
            "iv_attack": 0,
            "iv_defense": 31,
            "iv_special_attack": 16,
            "iv_special_defense": 31,
            "iv_speed": 22
        },
        "moves": {
            "move_1": "Astral Barrage",
            "move_2": "Psychic",
            "move_3": "Substitute",
            "move_4": "Protect"
        }
    },
    {
        "name": "Koraidon",
        "item": "Clear Amulet",
        "gender": "Genderless",
        "ability": "Orichalcum Pulse",
        "level": 50,
        "tera_type": "Fire",
        "nature": "Adamant",
        "evs": {
            "ev_hp": 204,
            "ev_attack": 116,
            "ev_defense": 4,
            "ev_special_attack": 252,
            "ev_special_defense": 52,
            "ev_speed": 132
        },
        "ivs": {
            "iv_hp": 31,
            "iv_attack": 0,
            "iv_defense": 31,
            "iv_special_attack": 31,
            "iv_special_defense": 31,
            "iv_speed": 26
        },
        "moves": {
            "move_1": "Flare Blitz",
            "move_2": "Collision Course",
            "move_3": "Flame Charge",
            "move_4": "Protect"
        }
    },
    {
        "name": "Tsareena",
        "item": "Loaded Dice",
        "gender": "Female",
        "ability": "Queenly Majesty",
        "level": 50,
        "tera_type": "Steel",
        "nature": "Adamant",
        "evs": {
            "ev_hp": 252,
            "ev_attack": 236,
            "ev_defense": 4,
            "ev_special_attack": 44,
            "ev_special_defense": 12,
            "ev_speed": 4
        },
        "ivs": {
            "iv_hp": 0,
            "iv_attack": 0,
            "iv_defense": 31,
            "iv_special_attack": 31,
            "iv_special_defense": 31,
            "iv_speed": 27
        },
        "moves": {
            "move_1": "Bullet Seed",
            "move_2": "Triple Axel",
            "move_3": "Taunt",
            "move_4": "Helping Hand"
        }
    },
    {
        "name": "Flamigo",
        "item": "Focus Sash",
        "gender": "Male",
        "ability": "Scrappy",
        "level": 50,
        "tera_type": "Ghost",
        "nature": "Adamant",
        "evs": {
            "ev_hp": 4,
            "ev_attack": 252,
            "ev_defense": 4,
            "ev_special_attack": 4,
            "ev_special_defense": 140,
            "ev_speed": 252
        },
        "ivs": {
            "iv_hp": 31,
            "iv_attack": 0,
            "iv_defense": 31,
            "iv_special_attack": 26,
            "iv_special_defense": 31,
            "iv_speed": 0
        },
        "moves": {
            "move_1": "Close Combat",
            "move_2": "Feint",
            "move_3": "Wide Guard",
            "move_4": "Protect"
        }
    },
    {
        "name": "Sandy Shocks",
        "item": "Assault Vest",
        "gender": "Genderless",
        "ability": "Protosynthesis",
        "level": 50,
        "tera_type": "Water",
        "nature": "Modest",
        "evs": {
            "ev_hp": 252,
            "ev_attack": 252,
            "ev_defense": 4,
            "ev_special_attack": 228,
            "ev_special_defense": 20,
            "ev_speed": 4
        },
        "ivs": {
            "iv_hp": 31,
            "iv_attack": 0,
            "iv_defense": 31,
            "iv_special_attack": 22,
            "iv_special_defense": 31,
            "iv_speed": 27
        },
        "moves": {
            "move_1": "Thunderbolt",
            "move_2": "Earth Power",
            "move_3": "Electroweb",
            "move_4": "Volt Switch"
        }
    },
    {
        "name": "Chi-Yu",
        "item": "Choice Scarf",
        "gender": "Genderless",
        "ability": "Beads of Ruin",
        "level": 50,
        "tera_type": "Ghost",
        "nature": "Modest",
        "evs": {
            "ev_hp": 20,
            "ev_attack": 4,
            "ev_defense": 4,
            "ev_special_attack": 228,
            "ev_special_defense": 4,
            "ev_speed": 252
        },
        "ivs": {
            "iv_hp": 0,
            "iv_attack": 0,
            "iv_defense": 31,
            "iv_special_attack": 20,
            "iv_special_defense": 31,
            "iv_speed": 0
        },
        "moves": {
            "move_1": "Heat Wave",
            "move_2": "Flamethrower",
            "move_3": "Dark Pulse",
            "move_4": "Overheat"
        }
    }
]